MANIFEST.in
README.md
setup.py
bin/index
bin/post_details
bin/search
bin/thread_details
moesearch/__init__.py
moesearch/api.py
moesearch/exceptions.py
moesearch/parser.py
moesearch/utilities.py
moesearch.egg-info/PKG-INFO
moesearch.egg-info/SOURCES.txt
moesearch.egg-info/dependency_links.txt
moesearch.egg-info/requires.txt
moesearch.egg-info/top_level.txt