Metadata-Version: 1.1
Name: moesearch
Version: 0.1.8
Summary: archive.moe Search REST API Library
Home-page: http://github.com/alfateam123/moesearch
Author: alfateam123
Author-email: alfateam123@gmail.com
License: UNKNOWN
Platform: UNKNOWN
Classifier: Development Status :: 4 - Beta
Classifier: Environment :: Web Environment
Classifier: Intended Audience :: Developers
Classifier: Topic :: Internet :: WWW/HTTP :: Dynamic Content :: Message Boards
Classifier: Topic :: Software Development :: Libraries :: Python Modules
